32_process.v
module mips_32 (clk1,clk2);

    input clk1,clk2;

    reg[2:0] ID_EX_type, EX_MEM_type, MEM_WB_type;
    reg[31:0] PC, IF_ID_IR, IF_ID_NPC;    //first stage
    reg[31:0] ID_EX_NPC, ID_EX_A, ID_EX_B, ID_EX_IMM, ID_EX_IR;
    reg[31:0] EX_MEM_IR, EX_MEM_B, EX_MEM_ALUout;
    reg EX_MEM_cond;
    reg [31:0] MEM_WB_IR, MEM_WB_ALUout, MEM_WB_LMD;
    reg [31:0] ID_EX_RA, EX_MEM_RA , MEM_WB_RA;

    reg [31:0] Reg [0:31];
    reg [31:0] Mem [0:1023];


    parameter ADD = 6'b000000, SUB = 6'b000001, AND = 6'b000010, OR = 6'b000011,
              SLT=6'b000100, MUL=6'b000101, HLT=6'b111111, LW=6'b001000,  
              SW=6'b001001, ADDI=6'b001010, SUBI=6'b001011,SLTI=6'b001100, 
              BNEQZ=6'b001101, BEQZ=6'b001110, JUMP = 6'b001111, JAL = 6'b010000, JR = 6'b010001;


    parameter RR_ALU = 3'b000, RM_ALU = 3'b001, LOAD = 3'b010, STORE = 3'b011,
                BRANCH = 3'b100, HALT = 3'b101, JMP = 3'b110;

    reg HALTED;
    reg TAKEN_BRANCH;
    reg JUMPER;
    reg STALL;



    always @(*)
    begin
        STALL = 0;
        if((EX_MEM_type == LOAD) && ((EX_MEM_IR[20:16] == IF_ID_IR[25:21]) || (EX_MEM_IR[20:16] == IF_ID_IR[20:16])))
        begin
            STALL = 1;
        end
    end


    // IF
    always @(posedge clk1)
    begin
        if(HALTED == 0)
        begin

            if(STALL)
            begin
                // IF_ID_IR        <= #1 Mem[PC-1];
                // IF_ID_NPC       <= #1 PC - 1;
                // PC              <= #1 PC - 1;
                
                IF_ID_IR  <= #1 IF_ID_IR;
                IF_ID_NPC <= #1 IF_ID_NPC;
                PC        <= #1 PC;
            end
            else if(((EX_MEM_IR[31:26] == BEQZ) && (EX_MEM_cond == 1)) || ((EX_MEM_IR[31:26] == BNEQZ) && (EX_MEM_cond == 0)))
            begin
                IF_ID_IR        <= #1 Mem[EX_MEM_ALUout];
                TAKEN_BRANCH    <= #1 1'b1;
                IF_ID_NPC       <= #1 EX_MEM_ALUout + 1;
                PC              <= #1 EX_MEM_ALUout + 1;
            end
            else
            begin
                IF_ID_IR        <= #1 Mem[PC];
                IF_ID_NPC       <= #1 PC + 1;
                PC              <= #1 PC + 1;
            end
            

        end
    end


    // ID
    always @(posedge clk2)
    begin

        
        
        if(HALTED == 0)
        begin


// stall for lw

        // STALL <= 0;
        // if((EX_MEM_type == LOAD) && ((EX_MEM_IR[20:16] == IF_ID_IR[26:21]) || (EX_MEM_IR[20:16] == IF_ID_IR[20:16])))
        // begin
        //     STALL = 1;
        // end


        
        if(STALL)
        begin
            ID_EX_IR <= #1 32'h0;
            ID_EX_A <= #1 0;
            ID_EX_B <= #1 0;
            ID_EX_NPC <= #1 0;
        end

        else begin

        //rs
        if(IF_ID_IR[25:21] == 5'b00000)
            ID_EX_A <= 0;
        else
            ID_EX_A <= #1 Reg[IF_ID_IR[25:21]];

        //rt
        if(IF_ID_IR[20:16] == 5'b00000)
            ID_EX_B <= 0;
        else
            ID_EX_B <= #1 Reg[IF_ID_IR[20:16]];


        ID_EX_NPC <= #1 IF_ID_NPC;
        ID_EX_IR <= #1 IF_ID_IR;
        
        ID_EX_IMM <= #1 {{16{IF_ID_IR[15]}}, {IF_ID_IR[15:0]}};

        case(IF_ID_IR[31:26])
            ADD,SUB,AND,OR,SLT,MUL : ID_EX_type <= #1 RR_ALU;
            ADDI,SUBI,SLTI         : ID_EX_type <= #1 RM_ALU;
            LW                     : ID_EX_type <= #1 LOAD;
            SW                     : ID_EX_type <= #1 STORE;
            BNEQZ,BEQZ             : ID_EX_type <= #1 BRANCH;
            JUMP,JAL,JR            : ID_EX_type <= #1 JMP;
            HLT                    : ID_EX_type <= #1 HALT;
            default                : ID_EX_type <= #1 HALT;
        endcase

        if(IF_ID_IR[31:26] == JUMP || IF_ID_IR[31:26] == JAL)
        begin
            PC <= #1 IF_ID_IR[25:0];
            ID_EX_RA <= #1 IF_ID_NPC;
            // TAKEN_BRANCH <= #1 1'b1;
        end
        else if(IF_ID_IR[31:26] == JR)
        begin
            PC <= #1 Reg[IF_ID_IR[25:21]];  
            // TAKEN_BRANCH <= #1 1'b1;
        end


        // Data forwarding
                    if(EX_MEM_type == RR_ALU && (EX_MEM_IR[15:11]) != 5'd0) 
                begin
                    if(EX_MEM_IR[15:11] == IF_ID_IR[25:21])
                    ID_EX_A <= #1 EX_MEM_ALUout;
                    if(EX_MEM_IR[15:11] == IF_ID_IR[20:16])
                    ID_EX_B <= #1 EX_MEM_ALUout;
                end
                
                if(EX_MEM_type == RM_ALU && (EX_MEM_IR[20:16]) != 5'd0)
                begin
                    if(EX_MEM_IR[20:16] == IF_ID_IR[25:21])
                    ID_EX_A <= #1 EX_MEM_ALUout;
                    if(EX_MEM_IR[20:16] == IF_ID_IR[20:16])
                    ID_EX_B <= #1 EX_MEM_ALUout;
                end

//LOAD data forwarding
            //  if (EX_MEM_type == LOAD && (EX_MEM_type[20:16] != 5'd0)) 
            // begin
            //     if (EX_MEM_IR[20:16] == IF_ID_IR[25:21])  
            //         ID_EX_A <= #1 MEM_WB_LMD;
            //     if (EX_MEM_IR[20:16] == IF_ID_IR[20:16])  
            //         ID_EX_B <= #1 MEM_WB_LMD;
            // end 
            
        
        end

        end

        
    end

    //EX
    always @(posedge clk1)
    begin
        if(HALTED == 0)
        begin
            EX_MEM_type <= #1 ID_EX_type;
            EX_MEM_IR <= #1 ID_EX_IR;
            EX_MEM_RA <= #1 ID_EX_RA;
            TAKEN_BRANCH <= #1 1'b0;

               
            // if (MEM_WB_type == LOAD && (MEM_WB_IR[20:16] != 5'd0)) 
            // begin
            //     if (MEM_WB_IR[20:16] == ID_EX_IR[25:21])  
            //         ID_EX_A <= #1 MEM_WB_LMD;
            //     if (MEM_WB_IR[20:16] == ID_EX_IR[20:16])  
            //         ID_EX_B <= #1 MEM_WB_LMD;
            // end 
            

              

            case(ID_EX_type)
                RR_ALU :begin
                        case(ID_EX_IR[31:26])
                            ADD:    EX_MEM_ALUout <= #1 ID_EX_A + ID_EX_B;
                            SUB:    EX_MEM_ALUout <= #1 ID_EX_A - ID_EX_B;
                            AND:    EX_MEM_ALUout <= #1 ID_EX_A & ID_EX_B;
                            OR:     EX_MEM_ALUout <= #1 ID_EX_A | ID_EX_B;
                            SLT:    EX_MEM_ALUout <= #1 ID_EX_A < ID_EX_B;
                            MUL:    EX_MEM_ALUout <= #1 ID_EX_A * ID_EX_B;
                            default:EX_MEM_ALUout <= #1 32'hxxxxxxxx;
                        endcase
                        end

                RM_ALU :begin
                        case(ID_EX_IR[31:26])
                            ADDI:   EX_MEM_ALUout <= #1 ID_EX_A + ID_EX_IMM;
                            SUBI:   EX_MEM_ALUout <= #1 ID_EX_A - ID_EX_IMM;
                            SLTI:   EX_MEM_ALUout <= #1 ID_EX_A < ID_EX_IMM;
                            default:EX_MEM_ALUout <= #1 32'hxxxxxxxx;
                        endcase
                        end

                LOAD,STORE :begin
                            EX_MEM_ALUout <= #1 ID_EX_A + ID_EX_IMM;
                            EX_MEM_B <= #1 ID_EX_B;
                            end

                BRANCH :    begin  //doubt
                            EX_MEM_ALUout <= #1 ID_EX_NPC + ID_EX_IMM;
                            EX_MEM_cond <= #1 (ID_EX_A == 0);
                            end

                // JMP    :    begin
                //             case(ID_EX_IR[31:26])
                            
                //             // JUMP    :  begin   EX_MEM_ALUout <= #1 {ID_EX_NPC[31:28],ID_EX_IR[25:0],2'b00}; end
                //             // JAL     :  begin   EX_MEM_ALUout <= #1 {ID_EX_NPC[31:28],ID_EX_IR[25:0],2'b00}; end
                //             // JR      :  begin   EX_MEM_ALUout <= #1 ID_EX_A; end
                //             endcase
                //             end

                            

            endcase
        end
    end
    

    //MEM
    always @(posedge clk2)
    begin
        if(HALTED == 0)
        begin
            MEM_WB_type <= #1 EX_MEM_type;
            MEM_WB_IR <= #1 EX_MEM_IR;
            MEM_WB_RA <= #1 EX_MEM_RA;

            case(EX_MEM_type)
                RR_ALU,RM_ALU : MEM_WB_ALUout <= #1 EX_MEM_ALUout;
                LOAD          : MEM_WB_LMD <= #1 Mem[EX_MEM_ALUout];
                STORE         : if(TAKEN_BRANCH == 0)
                                Mem[EX_MEM_ALUout] <= #1 EX_MEM_B;
            endcase
        end
    end


    //WB
    always @(posedge clk1)
    begin
        if(TAKEN_BRANCH == 0)
        begin
            if(MEM_WB_IR[31:26] == JAL)
            Reg[31] <= #1 MEM_WB_RA;
            else begin
            case(MEM_WB_type)
                RR_ALU : Reg[MEM_WB_IR[15:11]] <= #1 MEM_WB_ALUout;
                RM_ALU : Reg[MEM_WB_IR[20:16]] <= #1 MEM_WB_ALUout;
                LOAD   : Reg[MEM_WB_IR[20:16]] <= #1 MEM_WB_LMD;
                
                HALT   : HALTED                <= #1 1'b1;
            endcase
            end
            
        end
            
    end


endmodule

process_tb.v
module test_M132;

    reg clk1,clk2;

    mips_32 M1(.clk1(clk1),.clk2(clk2));

    integer i;

   


// Dual-Clk
    initial
    begin
        clk1 = 0; clk2 = 0;

        repeat(50)
        begin
            #5 clk1 = 1; #5 clk1 = 0;
            #5 clk2 = 1; #5 clk2 = 0;

        end
    end

    //initialisation
    initial
    begin
        for(i = 0;i<=31;i++)
        M1.Reg[i] = i;


        //Take Machine code from output.mem
        $readmemh("output.mem",M1.Mem);


//        M1.Mem[0] = 32'h28010009;  // ADDI  R1, R0, 9         --> R1 = 9
// M1.Mem[1] = 32'h40000008;  // JAL   8                 --> PC = 8, R31 = 2
// M1.Mem[2] = 32'h28020064;  // ADDI  R2, R0, 100       --> should be skipped due to jump
// M1.Mem[3] = 32'h0C631800;  // Dummy
// M1.Mem[4] = 32'h0C631800;  // Dummy
// M1.Mem[5] = 32'h44880000;  // JR    R1                --> PC = R1 = 9
// M1.Mem[6] = 32'h280400C8;  // ADDI  R4, R0, 200       --> should be skipped
// M1.Mem[7] = 32'h0C631800;  // Dummy
// M1.Mem[8] = 32'h28050037;  // ADDI  R5, R0, 55        --> should execute after JAL
// M1.Mem[9] = 32'h2806004D;  // ADDI  R6, R0, 77        --> should execute after JR
// M1.Mem[10] = 32'hFC000000; // HLT



//             M1.Mem[0] = 32'h280a00c8;  // ADDI  R10,R0,200 
// M1.Mem[1] = 32'h28020001;  // ADDI  R2,R0,1 
// M1.Mem[2] = 32'h0e94a000;  // OR    R20,R20,R20 -- dummy instr. 
// M1.Mem[3] = 32'h21430000;  // LW    R3,0(R10) 
// M1.Mem[4] = 32'h0e94a000;  // OR    R20,R20,R20 -- dummy instr. 
// M1.Mem[5] = 32'h14431000;  // Loop: MUL   R2,R2,R3 
// M1.Mem[6] = 32'h2c630001;  // SUBI  R3,R3,1 
// M1.Mem[7] = 32'h0e94a000;  // OR    R20,R20,R20 -- dummy instr. 
// M1.Mem[8] = 32'h3460fffc;  // BNEQZ R3,Loop  (i.e. -4 offset) 
// M1.Mem[9] = 32'h2542fffe;  // SW    R2,-2(R10) 
// M1.Mem[10] = 32'hfc000000; // HLT 








///This is for with handling hazards

//             M1.Mem[0] = 32'h280100C8;  // ADDI R1, R0, 200      ; R1 = 200
// M1.Mem[1] = 32'h28020032;  // ADDI R2, R0, 50       ; R2 = 50
// M1.Mem[2] = 32'h24220000;  // SW   R2, 0(R1)        ; MEM[200] = 50
// M1.Mem[3] = 32'h20230000;  // LW   R3, 0(R1)        ; R3 = MEM[200] = 50
// M1.Mem[4] = 32'h00632000;  // ADD  R4, R3, R3       ; R4 = R3 + R3 = 100
// M1.Mem[5] = 32'h04832800;  // SUB  R5, R4, R3       ; R5 = R4 - R3 = 50
// M1.Mem[6] = 32'h00000000;  // NOP / HLT (optional)  ; stop execution


//After assembly
// M1.Mem[0] = 32'h28010005;
// M1.Mem[1] = 32'h40000003;
// M1.Mem[2] = 32'hfc000000;
// M1.Mem[3] = 32'h2c210001;
// M1.Mem[4] = 32'h34200003;
// M1.Mem[5] = 32'hfc000000;







        M1.Mem[200] = 7;


        M1.HALTED = 0;
        M1.PC = 32'h0;
        M1.TAKEN_BRANCH = 0;

        #3000
        
        //  $display("R1 = %2d", M1.Reg[1]);
        //  $display("R2 = %2d", M1.Reg[2]); // Should be 0 (skipped)
        //  $display("R5 = %2d", M1.Reg[5]); // 55
        //  $display("R6 = %2d", M1.Reg[6]); // 77
        //  $display("R31 = %2d", M1.Reg[31]); // 2 (return address from JAL)
        //  $display("R4 = %2d", M1.Reg[4]);

        

        // for (i = 0; i <= 5; i = i + 1)
        // $display("Mem[%0d] = %h", i, M1.Mem[i]);

        // for (i=0; i<=6; i++) 
        // $display ("R%1d - %2d", i, M1.Reg[i]);

        // $display ("R1 - %2d", M1.Reg[1]);
        $display ("R31 - %2d", M1.Reg[31]);
         $display ("R12 - %2d", M1.Reg[12]);

        

        // $display ("Mem[200] = %2d,Mem[198] = %2d",M1.Mem[200],M1.Mem[198]);
        
    end

    initial
    begin
        $dumpfile("M1.vcd");
        $dumpvars(0,test_M132);
        $monitor("R1: %4d",M1.Reg[1]);
        #3000 $finish;

    end

endmodule

M1.vcd
$date
	Sat Aug 09 08:06:55 2025
$end
$version
	Icarus Verilog
$end
$timescale
	1s
$end
$scope module test_M132 $end
$var reg 1 ! clk1 $end
$var reg 1 " clk2 $end
$var integer 32 # i [31:0] $end
$scope module M1 $end
$var wire 1 ! clk1 $end
$var wire 1 " clk2 $end
$var parameter 6 $ ADD $end
$var parameter 6 % ADDI $end
$var parameter 6 & AND $end
$var parameter 6 ' BEQZ $end
$var parameter 6 ( BNEQZ $end
$var parameter 3 ) BRANCH $end
$var parameter 3 * HALT $end
$var parameter 6 + HLT $end
$var parameter 6 , JAL $end
$var parameter 3 - JMP $end
$var parameter 6 . JR $end
$var parameter 6 / JUMP $end
$var parameter 3 0 LOAD $end
$var parameter 6 1 LW $end
$var parameter 6 2 MUL $end
$var parameter 6 3 OR $end
$var parameter 3 4 RM_ALU $end
$var parameter 3 5 RR_ALU $end
$var parameter 6 6 SLT $end
$var parameter 6 7 SLTI $end
$var parameter 3 8 STORE $end
$var parameter 6 9 SUB $end
$var parameter 6 : SUBI $end
$var parameter 6 ; SW $end
$var reg 32 < EX_MEM_ALUout [31:0] $end
$var reg 32 = EX_MEM_B [31:0] $end
$var reg 32 > EX_MEM_IR [31:0] $end
$var reg 32 ? EX_MEM_RA [31:0] $end
$var reg 1 @ EX_MEM_cond $end
$var reg 3 A EX_MEM_type [2:0] $end
$var reg 1 B HALTED $end
$var reg 32 C ID_EX_A [31:0] $end
$var reg 32 D ID_EX_B [31:0] $end
$var reg 32 E ID_EX_IMM [31:0] $end
$var reg 32 F ID_EX_IR [31:0] $end
$var reg 32 G ID_EX_NPC [31:0] $end
$var reg 32 H ID_EX_RA [31:0] $end
$var reg 3 I ID_EX_type [2:0] $end
$var reg 32 J IF_ID_IR [31:0] $end
$var reg 32 K IF_ID_NPC [31:0] $end
$var reg 32 L MEM_WB_ALUout [31:0] $end
$var reg 32 M MEM_WB_IR [31:0] $end
$var reg 32 N MEM_WB_LMD [31:0] $end
$var reg 32 O MEM_WB_RA [31:0] $end
$var reg 3 P MEM_WB_type [2:0] $end
$var reg 32 Q PC [31:0] $end
$var reg 1 R STALL $end
$var reg 1 S TAKEN_BRANCH $end
$upscope $end
$upscope $end
$enddefinitions $end
$comment Show the parameter values. $end
$dumpall
b1001 ;
b1011 :
b1 9
b11 8
b1100 7
b100 6
b0 5
b1 4
b11 3
b101 2
b1000 1
b10 0
b1111 /
b10001 .
b110 -
b10000 ,
b111111 +
b101 *
b100 )
b1101 (
b1110 '
b10 &
b1010 %
b0 $
$end
#0
$dumpvars
0S
xR
b0 Q
bx P
bx O
bx N
bx M
bx L
bx K
bx J
bx I
bx H
bx G
bx F
bx E
bx D
bx C
0B
bx A
x@
bx ?
bx >
bx =
bx <
b100000 #
0"
0!
$end
#5
1!
#6
0R
b1 Q
b1 K
b111100000000000000000000000010 J
#10
0!
#15
b0 D
b0 C
1"
#16
b1 H
b10 Q
b110 I
b10 E
b111100000000000000000000000010 F
b1 G
#20
0"
#25
1!
#26
b1 ?
b111100000000000000000000000010 >
b110 A
b11 Q
b11 K
b0 J
#30
0!
#35
1"
#36
b1 O
b111100000000000000000000000010 M
b110 P
b0 I
b0 E
b0 F
b11 G
#40
0"
#45
1!
#46
b100 Q
b100 K
b111100000000000000000000000101 J
b0 <
b0 >
b0 A
#50
0!
#55
1"
#56
b100 H
b101 Q
b110 I
b101 E
b111100000000000000000000000101 F
b100 G
b0 L
b0 M
b0 P
#60
0"
#65
1!
#66
b100 ?
b111100000000000000000000000101 >
b110 A
b110 Q
b110 K
b0 J
#70
0!
#75
1"
#76
b100 O
b111100000000000000000000000101 M
b110 P
b0 I
b0 E
b0 F
b110 G
#80
0"
#85
1!
#86
b111 Q
b111 K
b101000000000010000000100101100 J
b0 >
b0 A
#90
0!
#95
1"
#96
b1 I
b100101100 E
b101000000000010000000100101100 F
b111 G
b1 D
b0 M
b0 P
#100
0"
#105
1!
#106
b100101100 <
b101000000000010000000100101100 >
b1 A
b1000 Q
b1000 K
b11111100000000000000000000000000 J
#110
0!
#115
b0 D
1"
#116
b100101100 L
b101000000000010000000100101100 M
b1 P
b101 I
b0 E
b11111100000000000000000000000000 F
b1000 G
#120
0"
#125
1!
#126
b1001 Q
b1001 K
bx J
b11111100000000000000000000000000 >
b101 A
#130
0!
#135
1"
#136
bx E
bx F
b1001 G
bx D
bx C
b11111100000000000000000000000000 M
b101 P
#140
0"
#145
1!
#146
1B
bx >
b1010 Q
b1010 K
